amzqr/__init__.py
amzqr/amzqr.py
amzqr/terminal.py
amzqr/mylibs/ECC.py
amzqr/mylibs/__init__.py
amzqr/mylibs/constant.py
amzqr/mylibs/data.py
amzqr/mylibs/draw.py
amzqr/mylibs/matrix.py
amzqr/mylibs/structure.py
amzqr/mylibs/theqrmodule.py
amzqr-0.0.1.dist-info/LICENSE.md
amzqr-0.0.1.dist-info/METADATA
amzqr-0.0.1.dist-info/WHEEL
amzqr-0.0.1.dist-info/entry_points.txt
amzqr-0.0.1.dist-info/top_level.txt
amzqr-0.0.1.dist-info/RECORD
