Metadata-Version: 2.1
Name: amzqr
Version: 0.0.1
Summary: Generater for amazing QR Codes. Including Common, Artistic and Animated QR Codes.
Home-page: https://github.com/hwxhw/amazing-qr
Author: hw
Author-email: xhaowen.xu@gmail.com
License: GPLv3
Download-URL: https://github.com/hwxhw/amazing-qr
Project-URL: Bug Tracker, https://github.com/hwxhw/amazing-qr/issues
Keywords: qr qrcode amazing artistic animated gif colorized
Platform: UNKNOWN
Classifier: Programming Language :: Python :: 3
Classifier: Operating System :: MacOS
Classifier: Operating System :: POSIX :: Linux
Classifier: Operating System :: Microsoft :: Windows
Classifier: License :: OSI Approved :: GNU General Public License v3 (GPLv3)
Requires-Python: >=3
Requires-Dist: imageio (>=1.5)
Requires-Dist: numpy (>=1.11.1)
Requires-Dist: Pillow (>=3.3.1)
